make87_messages/__init__.py
make87_messages/audio/__init__.py
make87_messages/audio/any_pb2.py
make87_messages/audio/any_pb2.pyi
make87_messages/audio/frame_aac_pb2.py
make87_messages/audio/frame_aac_pb2.pyi
make87_messages/audio/frame_opus_pb2.py
make87_messages/audio/frame_opus_pb2.pyi
make87_messages/audio/frame_pcm_s16le_pb2.py
make87_messages/audio/frame_pcm_s16le_pb2.pyi
make87_messages/core/__init__.py
make87_messages/core/empty_pb2.py
make87_messages/core/empty_pb2.pyi
make87_messages/core/header_pb2.py
make87_messages/core/header_pb2.pyi
make87_messages/datetime/__init__.py
make87_messages/datetime/range_pb2.py
make87_messages/datetime/range_pb2.pyi
make87_messages/datetime/timestamp_pb2.py
make87_messages/datetime/timestamp_pb2.pyi
make87_messages/detection/__init__.py
make87_messages/detection/box/__init__.py
make87_messages/detection/box/box_2d_pb2.py
make87_messages/detection/box/box_2d_pb2.pyi
make87_messages/detection/box/boxes_2d_pb2.py
make87_messages/detection/box/boxes_2d_pb2.pyi
make87_messages/detection/ontology/__init__.py
make87_messages/detection/ontology/model_ontology_pb2.py
make87_messages/detection/ontology/model_ontology_pb2.pyi
make87_messages/file/__init__.py
make87_messages/file/simple_file_pb2.py
make87_messages/file/simple_file_pb2.pyi
make87_messages/geometry/__init__.py
make87_messages/geometry/box/__init__.py
make87_messages/geometry/box/box_2d_aligned_pb2.py
make87_messages/geometry/box/box_2d_aligned_pb2.pyi
make87_messages/geometry/box/box_2d_pb2.py
make87_messages/geometry/box/box_2d_pb2.pyi
make87_messages/geometry/box/boxes_2d_aligned_pb2.py
make87_messages/geometry/box/boxes_2d_aligned_pb2.pyi
make87_messages/geometry/box/boxes_2d_pb2.py
make87_messages/geometry/box/boxes_2d_pb2.pyi
make87_messages/image/__init__.py
make87_messages/image/compressed/__init__.py
make87_messages/image/compressed/image_jpeg_pb2.py
make87_messages/image/compressed/image_jpeg_pb2.pyi
make87_messages_pb5-0.2.8.dist-info/METADATA
make87_messages_pb5-0.2.8.dist-info/WHEEL
make87_messages_pb5-0.2.8.dist-info/top_level.txt
make87_messages_pb5-0.2.8.dist-info/RECORD
