Metadata-Version: 2.4
Name: make87_messages_pb5
Version: 0.2.8
Author-email: Nisse Knudsen <nisse@make87.com>
Requires-Python: <3.13,>=3.9
Requires-Dist: protobuf<6.0,>=5.26
Provides-Extra: dev
Requires-Dist: pre-commit; extra == "dev"
